{
  "schema_version": "1.0",
  "pipeline": "EDCR",
  "phases": {
    "init": {
      "status": "completed",
      "started_at": "2026-05-24T22:57:00Z",
      "completed_at": "2026-05-24T22:57:00Z",
      "artifacts": [
        "evidence/context.json",
        "evidence/workflow.json"
      ]
    },
    "scan": {
      "status": "completed",
      "started_at": "2026-05-26T06:00:00Z",
      "completed_at": "2026-05-26T06:05:00Z",
      "artifacts": [
        "evidence/discovery/candidates.md",
        "evidence/discovery/signals/s1-packages.json",
        "evidence/discovery/signals/s2-schema.json",
        "evidence/discovery/signals/s3-entrypoints.json",
        "evidence/discovery/signals/s4-frontend.json",
        "evidence/security/security-signals.json",
        "evidence/security/security-dependencies.json",
        "evidence/security/signals/ss1-static.json",
        "evidence/security/signals/ss3-config.json",
        "evidence/security/signals/ss4-data-sensitivity.json",
        "evidence/qa/qa-signals.json",
        "evidence/qa/test-inventory.json",
        "evidence/qa/coverage/coverage-map.json",
        "evidence/qa/testability/testability-findings.json",
        "evidence/qa/environments/ci-map.json",
        "evidence/qa/environments/environment-map.json",
        "evidence/qa/environments/flaky-tests.json"
      ]
    },
    "discover": {
      "status": "completed",
      "started_at": "2026-05-25T02:21:44.733947Z",
      "completed_at": "2026-05-25T02:21:44.733947Z",
      "artifacts": [
        "evidence/discovery/analysis.md",
        "evidence/discovery/coverage.md",
        "evidence/discovery/l1-capabilities.md",
        "evidence/discovery/l2-capabilities.md",
        "evidence/discovery/domain-model.md",
        "evidence/discovery/blueprint-comparison.md",
        "evidence/discovery/security-context.json",
        "evidence/qa/qa-context.json"
      ]
    },
    "report": {
      "status": "completed",
      "started_at": "2026-05-25T02:27:41.398251Z",
      "completed_at": "2026-05-25T02:27:41.398251Z",
      "artifacts": [
        "evidence/reports/stakeholder-report.md",
        "evidence/reports/architect-report.md",
        "evidence/reports/dev-report.md",
        "evidence/reports/sdet-report.md"
      ]
    },
    "assess": {
      "status": "completed",
      "started_at": "2026-05-25T12:36:26.171947Z",
      "completed_at": "2026-05-25T12:36:26.171947Z",
      "artifacts": [
        "evidence/security/threats/BC-001.json",
        "evidence/security/threats/BC-002.json",
        "evidence/security/threats/BC-003.json",
        "evidence/security/threats/BC-004.json",
        "evidence/security/threats/BC-005.json",
        "evidence/security/threats/BC-006.json",
        "evidence/security/vulnerabilities/catalog.json",
        "evidence/security/controls/control-map.json",
        "evidence/security/risk-scores.json",
        "evidence/security/cross-capability-risks.json",
        "evidence/security/gaps.json",
        "evidence/qa/qa-risk-scores.json",
        "evidence/qa/qa-gaps.json",
        "evidence/risk/unified-risk-map.json"
      ]
    },
    "generate": {
      "status": "pending",
      "started_at": null,
      "completed_at": null,
      "artifacts": []
    },
    "finish": {
      "status": "completed",
      "started_at": "2026-05-25T12:38:19.790954Z",
      "completed_at": "2026-05-25T12:38:19.790954Z",
      "artifacts": [
        "evidence/acceptance-check.md",
        "evidence/README.md",
        "evidence/manifest.json",
        "evidence/generate/handoff/platform-sre/README.md",
        "evidence/generate/handoff/voice-engineering/README.md",
        "evidence/generate/handoff/operations-devops/README.md",
        "evidence/generate/handoff/shared/infrastructure.md",
        "evidence/generate/handoff/shared/compliance-gaps.md"
      ]
    }
  },
  "adaptations": {
    "db_schema_analysis": "auto",
    "frontend_analysis": "auto",
    "coverage_source": "proxy"
  },
  "notes": [
    "coverage_report: not-collected (no coverage tool configured; project uses Docker-based integration tests)",
    "ndepend_export: not-collected (C project with no .NET assemblies)",
    "db_schema_export: not-collected (PostgreSQL schema is in db/init/ SQL files, not an exported dump)",
    "flaky_test_history: not-collected (not available)",
    "defect_export: not-collected (not available)",
    "entry_point_list: not-collected (not available)",
    "detect-stack: primary_languages skewed by .ansible-venv/ (4959 files); real project is Docker/C/Python/PHP",
    "SS2: cve_lookup not-collected (no vulnerability data source wired in)",
    "QS2: coverage_source=proxy (no coverage report configured)",
    "QS4: flaky_tests not-collected (inputs.flaky_test_history is null)",
    "D8: TM Forum missing items flagged for stakeholder clarification (billing, product catalog, partner mgmt)",
    "D3: File coverage 92% (45 capability + 12 infra = 57/62 significant files)",
    "report: security report skipped \u2014 assess not done",
    "assess: BC-001 through BC-006 have unified composite 'partial' because QA signals not fully collected",
    "assess: 8 vulnerabilities cataloged (1 Confirmed, 3 Probable, 4 Potential)",
    "assess: 3 cross-capability systemic risks identified",
    "scan-rescan-2026-05-26: Re-scan triggered after docs/aide/ creation (vision.md, roadmap.md, progress.md, queue-001.md). No meaningful changes to capability, security, or QA signals. Prior scan artifacts remain valid. docs/aide/ is planning documentation (domain_suggestive=false, LOW confidence) and does not affect S1-S5, SS1-SS4, or QS1-QS4."
  ]
}